tracker/__init__.py
tracker/_version.py
tracker/geometry.py
tracker/units.py
tracker/analysis/__init__.py
tracker/analysis/track.py
tracker/analysis/vertex.py
tracker/io/__init__.py
tracker/io/reader.py
tracker/io/script.py
tracker/io/writer.py
tracker/ui/__init__.py
tracker/ui/canvas.py
tracker/util/__init__.py
tracker/util/core.py
tracker/util/math.py
mathusla_tracker-0.0.2.dist-info/LICENSE
mathusla_tracker-0.0.2.dist-info/METADATA
mathusla_tracker-0.0.2.dist-info/WHEEL
mathusla_tracker-0.0.2.dist-info/top_level.txt
mathusla_tracker-0.0.2.dist-info/RECORD
