Metadata-Version: 2.1
Name: mathusla-tracker
Version: 0.0.2
Summary: MATHUSLA Tracking Algorithm
Home-page: https://github.com/MATHUSLA/tracker
Author: Brandon Gomes
Author-email: bhgomes.github@gmail.com
License: MIT
Platform: UNKNOWN
Classifier: License :: OSI Approved :: MIT License
Classifier: Programming Language :: Python
Classifier: Programming Language :: Python :: 3
Classifier: Programming Language :: Python :: 3 :: Only
Classifier: Programming Language :: Python :: 3.7
Classifier: Development Status :: 1 - Planning
Classifier: Intended Audience :: Developers
Classifier: Intended Audience :: Science/Research
Classifier: Topic :: Scientific/Engineering :: Physics
Classifier: Topic :: Software Development :: Libraries
Classifier: Topic :: Utilities
Requires-Python: >=3.7.0
Requires-Dist: pytest
Requires-Dist: uptrack
Requires-Dist: scikit-hep
Requires-Dist: pint
Requires-Dist: unyt
Requires-Dist: uncertainties
Requires-Dist: aenum
